Metadata-Version: 1.0
Name: static-grader
Version: 0.2.0
Summary: A Static grader
Home-page: UNKNOWN
Author: The Data Incubator
Author-email: UNKNOWN
License: UNKNOWN
Platform: UNKNOWN
